secure_logger/__about__.py
secure_logger/__init__.py
secure_logger/__version__.py
secure_logger/conf.py
secure_logger/decorators.py
secure_logger/exceptions.py
secure_logger/masked_dict.py
secure_logger/tests/__init__.py
secure_logger/tests/test_class_decorator.py
secure_logger/tests/test_class_method_decorator.py
secure_logger/tests/test_custom_params.py
secure_logger/tests/test_function_decorator.py
secure_logger/tests/test_masked_dict.py
secure_logger/tests/test_masked_dict_sensitivity.py
secure_logger-0.2.2.dist-info/licenses/LICENSE.txt
secure_logger-0.2.2.dist-info/METADATA
secure_logger-0.2.2.dist-info/WHEEL
secure_logger-0.2.2.dist-info/top_level.txt
secure_logger-0.2.2.dist-info/RECORD
