Metadata-Version: 2.4
Name: secure-logger
Version: 0.2.2
Summary: A decorator to generate redacted and nicely formatted log entries
Home-page: https://github.com/FullStackWithLawrence/secure-logger
Author: Lawrence McDaniel
Author-email: lpm0073@gmail.com
Maintainer: Lawrence McDaniel
Maintainer-email: lpm0073@gmail.com
License: GPL-3.0-or-later
Project-URL: Source, https://github.com/FullStackWithLawrence/secure-logger
Project-URL: Documentation, https://pypi.org/project/secure-logger/
Project-URL: Changelog, https://github.com/FullStackWithLawrence/secure-logger/blob/main/CHANGELOG.md
Project-URL: Security, https://github.com/FullStackWithLawrence/secure-logger/blob/main/SECURITY.md
Project-URL: Code of Conduct, https://github.com/FullStackWithLawrence/secure-logger/blob/main/CODE_OF_CONDUCT.md
Project-URL: Tracker, https://github.com/FullStackWithLawrence/secure-logger/issues
Keywords: logging,security,redaction
Platform: any
Classifier: Development Status :: 4 - Beta
Classifier: Environment :: Web Environment
Classifier: Intended Audience :: Developers
Classifier: Operating System :: OS Independent
Classifier: Programming Language :: Python
Classifier: Programming Language :: Python :: 3
Classifier: Programming Language :: Python :: 3 :: Only
Classifier: Programming Language :: Python :: 3.8
Classifier: Programming Language :: Python :: 3.9
Classifier: Programming Language :: Python :: 3.10
Classifier: Programming Language :: Python :: 3.11
Classifier: Programming Language :: Python :: 3.12
Classifier: Programming Language :: Python :: Implementation :: PyPy
Classifier: Topic :: Utilities
Requires-Python: >=3.6
License-File: LICENSE.txt
Requires-Dist: pydantic>=2.5.0
Dynamic: author
Dynamic: author-email
Dynamic: classifier
Dynamic: description
Dynamic: description-content-type
Dynamic: home-page
Dynamic: keywords
Dynamic: license
Dynamic: license-file
Dynamic: maintainer
Dynamic: maintainer-email
Dynamic: platform
Dynamic: project-url
Dynamic: requires-dist
Dynamic: requires-python
Dynamic: summary
